{
  "$schema": "http://json-schema.org/draft-04/schema#",
  "title": "Retrieve Coding Out underpayment and debt amounts",
  "description": "Retrieve Coding Out underpayment and debt amounts",
  "type": "object",
  "properties": {
    "source": {
      "description": "Specifies the source of data.",
      "type": "string",
      "enum": [
        "hmrcHeld",
        "user"
      ]
    },
    "selfAssessmentUnderPayments": {
      "type": "array",
      "description": "Array containing details of coding out Self Assessment underpayments.",
      "minItems": 1,
      "items": {
        "type": "object",
        "properties": {
          "amount": {
            "description": "The total coding out amount attributed to Self Assessment underpayments. The value must be between 0 and 99999999999.99 up to 2 decimal places.",
            "type": "number",
            "multipleOf": 0.01,
            "minimum": 0.00,
            "maximum": 99999999999.99,
            "example": "5000.99"
          },
          "relatedTaxYear": {
            "description": "The tax year related to the underpayment.",
            "type": "string",
            "example": "2021-22"
          },
          "submittedOn": {
            "description": "The date the coding out information was added. It is either the latest change date held within HMRC or the latest user submitted date. It is in the format YYYY-MM-DDThh:mm:ssZ.",
            "type": "string",
            "example": "2020-07-06T09:37:17Z"
          }
        },
        "required": [
          "amount",
          "relatedTaxYear",
          "submittedOn"
        ]
      }
    },
    "payeUnderpayments": {
      "type": "array",
      "description": "Array containing details of coding out PAYE underpayments.",
      "minItems": 1,
      "items": {
        "type": "object",
        "properties": {
          "amount": {
            "description": "The total coding out amount attributed to PAYE underpayments. The value must be between 0 and 99999999999.99 up to 2 decimal places.",
            "type": "number",
            "multipleOf": 0.01,
            "minimum": 0.00,
            "maximum": 99999999999.99,
            "example": "5000.99"
          },
          "relatedTaxYear": {
            "description": "The tax year related to the underpayment.",
            "type": "string",
            "example": "2021-22"
          },
          "submittedOn": {
            "description": "The date the coding out information was added. It is either the latest change date held within HMRC or the latest user submitted date. It is in the format YYYY-MM-DDThh:mm:ssZ.",
            "type": "string",
            "example": "2020-07-06T09:37:17Z"
          }
        },
        "required": [
          "amount",
          "relatedTaxYear",
          "submittedOn"
        ]
      }
    },
    "debts": {
      "type": "array",
      "description": "Array containing details of coding out debts.",
      "minItems": 1,
      "items": {
        "type": "object",
        "properties": {
          "amount": {
            "description": "The amount of the debt. The value must be between 0 and 99999999999.99 up to 2 decimal places.",
            "type": "number",
            "multipleOf": 0.01,
            "minimum": 0.00,
            "maximum": 99999999999.99,
            "example": "5000.99"
          },
          "relatedTaxYear": {
            "description": "The tax year related to the debt.",
            "type": "string",
            "example": "2021-22"
          },
          "submittedOn": {
            "description": "The date the coding out information was added. It is either the latest change date held within HMRC or the latest user submitted date. It is in the format YYYY-MM-DDThh:mm:ssZ.",
            "type": "string",
            "example": "2020-07-06T09:37:17Z"
          }
        },
        "required": [
          "amount",
          "relatedTaxYear",
          "submittedOn"
        ]
      }
    },
    "inYearAdjustments": {
      "type": "object",
      "description": "Object containing details of in-year adjusted coding out underpayments and debts.",
      "properties": {
        "amount": {
          "description": "The amount of the in-year adjustment. The value must be between 0 and 99999999999.99 up to 2 decimal places.",
          "type": "number",
          "multipleOf": 0.01,
          "minimum": 0.00,
          "maximum": 99999999999.99,
          "example": "5000.99"
        },
        "relatedTaxYear": {
          "description": "The tax year related to the in-year adjustment.",
          "type": "string",
          "example": "2021-22"
        },
        "submittedOn": {
          "description": "The date the coding out information was added. It is either the latest change date held within HMRC or the latest user submitted date. It is in the format YYYY-MM-DDThh:mm:ssZ.",
          "type": "string",
          "example": "2020-07-06T09:37:17Z"
        }
      },
      "required": [
        "amount",
        "relatedTaxYear",
        "submittedOn"
      ]
    },
    "links": {
      "type": "array",
      "items": {
        "type": "object",
        "description": "A list of endpoint links that indicate possible actions related to the current resource",
        "properties": {
          "href": {
            "description": "The relative url of the endpoint",
            "type": "string",
            "example": "/accounts/self-assessment/TC663795B/2021-22/collection/tax-code"
          },
          "rel": {
            "description": "A label for the endpoint, which describes how it is related to the current resource. The rel will be self where the action is retrieval of the same resource",
            "type": "string",
            "enum": [
              "create-or-amend-coding-out-underpayments",
              "self",
              "delete-coding-out-underpayments"
            ]
          },
          "method": {
            "description": "The HTTP method type for the endpoint",
            "type": "string",
            "enum": [
              "PUT",
              "GET",
              "DELETE"
            ]
          }
        },
        "required": [
          "href",
          "rel",
          "method"
        ]
      }
    }
  },
  "required": [
    "source",
    "links"
  ]
}